crimson/templator/__RemoveLines.py
crimson/templator/__init__.py
crimson/templator/_extract.py
crimson/templator/_utils.py
crimson_templator-0.2.2.dist-info/LICENSE
crimson_templator-0.2.2.dist-info/METADATA
crimson_templator-0.2.2.dist-info/WHEEL
crimson_templator-0.2.2.dist-info/top_level.txt
crimson_templator-0.2.2.dist-info/RECORD
