Metadata-Version: 2.1
Name: crimson-templator
Version: 0.2.2
Summary: Template Tools.
Author-email: Sisung Kim <sisung.kim1@gmail.com>
Project-URL: Homepage, https://github.com/crimson206/templator
Project-URL: Bug Tracker, https://github.com/crimson206/templator/issues
Classifier: Programming Language :: Python :: 3
Classifier: Programming Language :: Python :: 3.9
Classifier: Programming Language :: Python :: 3.10
Classifier: Programming Language :: Python :: 3.11
Classifier: Programming Language :: Python :: 3.12
Classifier: Intended Audience :: Developers
Classifier: Topic :: Software Development :: Libraries :: Python Modules
Classifier: License :: OSI Approved :: MIT License
Classifier: Operating System :: OS Independent
Classifier: Typing :: Typed
Requires-Python: >=3.9
License-File: LICENSE
Requires-Dist: pydantic
Requires-Dist: crimson-intelli-type==0.4.0
